README.md
SETUP.py
setup.py
Topsis_Dhanvi9_101903427.egg-info/PKG-INFO
Topsis_Dhanvi9_101903427.egg-info/SOURCES.txt
Topsis_Dhanvi9_101903427.egg-info/dependency_links.txt
Topsis_Dhanvi9_101903427.egg-info/top_level.txt