Metadata-Version: 1.1
Name: Topsis-Dhanvi9-101903427
Version: 0.0.1
Summary: Topsis python for decision making based on multiple factors
Home-page: UNKNOWN
Author: Dhanvi Bansal
Author-email: dhanvi884@gmail.com
License: MIT
Keywords: topsis
Platform: UNKNOWN
Classifier: Development Status :: 5 - Production/Stable
Classifier: Intended Audience :: Education
Classifier: Operating System :: Microsoft :: Windows :: Windows 10
Classifier: License :: OSI Approved :: MIT License
Classifier: Programming Language :: Python :: 3
